vercel/__main__.py
vercel/client.py
vercel/env.py
vercel/headers.py
vercel/py.typed
vercel/_telemetry/__init__.py
vercel/_telemetry/client.py
vercel/_telemetry/credentials.py
vercel/_telemetry/tracker.py
vercel/blob/__init__.py
vercel/blob/aio.py
vercel/blob/api.py
vercel/blob/client.py
vercel/blob/errors.py
vercel/blob/ops.py
vercel/blob/types.py
vercel/blob/utils.py
vercel/blob/multipart/__init__.py
vercel/blob/multipart/api.py
vercel/blob/multipart/core.py
vercel/blob/multipart/uploader.py
vercel/cache/__init__.py
vercel/cache/aio.py
vercel/cache/cache_build.py
vercel/cache/cache_in_memory.py
vercel/cache/context.py
vercel/cache/purge.py
vercel/cache/runtime_cache.py
vercel/cache/types.py
vercel/cache/utils.py
vercel/deployments/__init__.py
vercel/deployments/aio.py
vercel/deployments/client.py
vercel/deployments/deployments.py
vercel/functions/__init__.py
vercel/functions/aio.py
vercel/oidc/__init__.py
vercel/oidc/aio.py
vercel/oidc/credentials.py
vercel/oidc/token.py
vercel/oidc/types.py
vercel/oidc/utils.py
vercel/projects/__init__.py
vercel/projects/aio.py
vercel/projects/client.py
vercel/projects/projects.py
vercel-0.3.8.dist-info/METADATA
vercel-0.3.8.dist-info/WHEEL
vercel-0.3.8.dist-info/entry_points.txt
vercel-0.3.8.dist-info/top_level.txt
vercel-0.3.8.dist-info/RECORD
