Metadata-Version: 2.4
Name: vercel
Version: 0.3.8
Summary: Python SDK for Vercel
License-Expression: MIT
Requires-Python: >=3.10
Requires-Dist: vercel-sandbox>=0.0.4
Requires-Dist: httpx>=0.27.0
Requires-Dist: pydantic>=2.7.0
Requires-Dist: anyio>=4.0.0
Requires-Dist: python-dotenv
